PyAPplus64/__init__.py
PyAPplus64/applus.py
PyAPplus64/applus_db.py
PyAPplus64/applus_job.py
PyAPplus64/applus_scripttool.py
PyAPplus64/applus_server.py
PyAPplus64/applus_sysconf.py
PyAPplus64/applus_usexml.py
PyAPplus64/duplicate.py
PyAPplus64/pandas.py
PyAPplus64/py.typed
PyAPplus64/sql_utils.py
PyAPplus64/utils.py
PyAPplus64-1.1.2.dist-info/LICENSE
PyAPplus64-1.1.2.dist-info/METADATA
PyAPplus64-1.1.2.dist-info/WHEEL
PyAPplus64-1.1.2.dist-info/top_level.txt
PyAPplus64-1.1.2.dist-info/RECORD
