Metadata-Version: 2.1
Name: PyAPplus64
Version: 1.1.2
Summary: Verschiedene Hilfsmittel, um mit dem ERP System APplus zu interagieren. Dieses Packet wurde für APplus 6.4 entwickelt, funktioniert vermutlich aber auch mit anderen Versionen.
Author-email: Thomas Tuerk <kontakt@thomas-tuerk.de>
Project-URL: homepage, https://www.thomas-tuerk.de/de/pyapplus64
Project-URL: repository, https://git.thomas-tuerk.de/thtuerk/PyAPplus64
Project-URL: documentation, https://www.thomas-tuerk.de/assets/PyAPplus64/html/index.html
Classifier: Programming Language :: Python :: 3
Classifier: License :: OSI Approved :: MIT License
Classifier: Development Status :: 3 - Alpha
Classifier: Intended Audience :: Other Audience
Classifier: Operating System :: Microsoft :: Windows
Requires-Python: >=3.6
License-File: LICENSE
Requires-Dist: pyodbc
Requires-Dist: PyYAML
Requires-Dist: SQLAlchemy
Requires-Dist: pandas
Requires-Dist: XlsxWriter
Requires-Dist: zeep
Requires-Dist: pysimplegui
Requires-Dist: sqlparse
Requires-Dist: sqlfmt
